telebulk/__init__.py
telebulk/__main__.py
telebulk-0.1.3.dist-info/METADATA
telebulk-0.1.3.dist-info/WHEEL
telebulk-0.1.3.dist-info/entry_points.txt
telebulk-0.1.3.dist-info/licenses/LICENSE.txt
telebulk-0.1.3.dist-info/RECORD
