Metadata-Version: 2.4
Name: telebulk
Version: 0.1.3
Summary: Execute actions on multiple Telegram users or groups
License-Expression: EUPL-1.2
License-File: LICENSE.txt
Keywords: telegram,cli
Author: Stefano Pigozzi
Author-email: me@steffo.eu
Maintainer: Stefano Pigozzi
Maintainer-email: me@steffo.eu
Requires-Python: >=3.13,<4.0
Classifier: Development Status :: 3 - Alpha
Classifier: Environment :: Console
Classifier: Intended Audience :: End Users/Desktop
Classifier: License :: OSI Approved :: European Union Public Licence 1.2 (EUPL 1.2)
Classifier: Natural Language :: English
Classifier: Operating System :: OS Independent
Classifier: Programming Language :: Python :: 3.13
Classifier: Topic :: Communications :: Chat
Requires-Dist: click (>=8.3.0,<9.0.0)
Requires-Dist: telethon (>=1.41.2,<2.0.0)
Project-URL: Issues, https://forge.steffo.eu/steffo/telebulk/issues
Project-URL: Source, https://forge.steffo.eu/steffo/telebulk
